elexonpy/__init__.py
elexonpy/api_client.py
elexonpy/configuration.py
elexonpy/rest.py
elexonpy/api/__init__.py
elexonpy/api/availability_api.py
elexonpy/api/balancing_mechanism_dynamic_api.py
elexonpy/api/balancing_mechanism_physical_api.py
elexonpy/api/balancing_services_adjustment___disaggregated_api.py
elexonpy/api/balancing_services_adjustment___net_api.py
elexonpy/api/bid_offer_acceptances_api.py
elexonpy/api/bid_offer_api.py
elexonpy/api/credit_default_notice_api.py
elexonpy/api/datasets_api.py
elexonpy/api/demand_api.py
elexonpy/api/demand_forecast_api.py
elexonpy/api/generation_api.py
elexonpy/api/generation_forecast_api.py
elexonpy/api/health_check_api.py
elexonpy/api/indicated_forecast_api.py
elexonpy/api/indicative_imbalance_settlement_api.py
elexonpy/api/legacy_api.py
elexonpy/api/loss_of_load_probability_and_de_rated_margin_api.py
elexonpy/api/margin_forecast_api.py
elexonpy/api/market_index_api.py
elexonpy/api/non_bm_stor_api.py
elexonpy/api/non_bm_volumes_api.py
elexonpy/api/reference_api.py
elexonpy/api/remit_api.py
elexonpy/api/rolling_system_demand_api.py
elexonpy/api/so_so_prices_api.py
elexonpy/api/surplus_forecast_api.py
elexonpy/api/system_api.py
elexonpy/api/system_forecast_api.py
elexonpy/api/temperature_api.py
elexonpy/models/__init__.py
elexonpy/models/insights_api_legacy_interoperability_legacy_remit_detail_body.py
elexonpy/models/insights_api_legacy_interoperability_legacy_remit_detail_item.py
elexonpy/models/insights_api_legacy_interoperability_legacy_remit_detail_list.py
elexonpy/models/insights_api_legacy_interoperability_legacy_remit_detail_metadata.py
elexonpy/models/insights_api_legacy_interoperability_legacy_remit_detail_response.py
elexonpy/models/insights_api_legacy_interoperability_legacy_remit_list_item.py
elexonpy/models/insights_api_legacy_interoperability_legacy_remit_list_metadata.py
elexonpy/models/insights_api_legacy_interoperability_legacy_remit_list_response.py
elexonpy-1.0.15.dist-info/LICENSE
elexonpy-1.0.15.dist-info/METADATA
elexonpy-1.0.15.dist-info/WHEEL
elexonpy-1.0.15.dist-info/top_level.txt
elexonpy-1.0.15.dist-info/RECORD
