Metadata-Version: 2.1
Name: elexonpy
Version: 1.0.15
Summary: Elexon Python Client
Author-email: Richa Sharma <onlinericha19@gmail.com>, Peter Dudfield <info@openclimatefix.org>
Project-URL: Homepage, https://github.com/openclimatefix/Elexonpy
Project-URL: Source Code, https://github.com/openclimatefix/Elexonpy
Keywords: Swagger,Elexon API,Python Client
Classifier: Programming Language :: Python :: 3
Classifier: License :: OSI Approved :: MIT License
Classifier: Operating System :: OS Independent
Requires-Python: >=3.6
License-File: LICENSE
Requires-Dist: urllib3>=1.15
Requires-Dist: six>=1.10
Requires-Dist: certifi
Requires-Dist: python-dateutil
Requires-Dist: pandas>=2.0.0
Requires-Dist: numpy>=1.24.0
Requires-Dist: requests
Requires-Dist: requests-mock
Provides-Extra: all
Requires-Dist: elexonpy[dev]; extra == "all"
Provides-Extra: dev
Requires-Dist: black; extra == "dev"
Requires-Dist: flake8; extra == "dev"
Requires-Dist: isort; extra == "dev"
Requires-Dist: pre-commit; extra == "dev"
Requires-Dist: pytest; extra == "dev"
Requires-Dist: pytest-cov; extra == "dev"
Requires-Dist: pytest-mock; extra == "dev"
